{"_product_image_gallery":["https:\/\/i.content4travel.com\/cms\/img\/u\/desktop\/prodsliderphoto\/\/hrgpalg_0.jpg?version=58?version=1","https:\/\/i.content4travel.com\/cms\/img\/u\/desktop\/prodsliderphoto\/\/hrgpalg_3.jpg?version=58?version=1","https:\/\/i.content4travel.com\/cms\/img\/u\/desktop\/prodsliderphoto\/\/hrgpalg_4.jpg?version=58?version=1","https:\/\/i.content4travel.com\/cms\/img\/u\/desktop\/prodsliderphoto\/\/hrgpalg_5.jpg?version=58?version=1","https:\/\/i.content4travel.com\/cms\/img\/u\/desktop\/prodsliderphoto\/\/hrgpalg_6.jpg?version=58?version=1","https:\/\/i.content4travel.com\/cms\/img\/u\/desktop\/prodsliderphoto\/\/hrgpalg_7.jpg?version=58?version=1","https:\/\/i.content4travel.com\/cms\/img\/u\/desktop\/prodsliderphoto\/\/hrgpalg_8.jpg?version=58?version=1","https:\/\/i.content4travel.com\/cms\/img\/u\/desktop\/prodsliderphoto\/\/hrgpalg_9.jpg?version=58?version=1","https:\/\/i.content4travel.com\/cms\/img\/u\/desktop\/prodsliderphoto\/\/hrgpalg_13.jpg?version=58?version=1","https:\/\/i.content4travel.com\/cms\/img\/u\/desktop\/prodsliderphoto\/\/hrgpalg_16.jpg?version=58?version=1","https:\/\/i.content4travel.com\/cms\/img\/u\/desktop\/prodsliderphoto\/\/hrgpalg_19.jpg?version=58?version=1","https:\/\/i.content4travel.com\/cms\/img\/u\/desktop\/prodsliderphoto\/\/hrgpalg_20.jpg?version=58?version=1","https:\/\/i.content4travel.com\/cms\/img\/u\/desktop\/prodsliderphoto\/\/hrgpalg_21.jpg?version=58?version=1","https:\/\/i.content4travel.com\/cms\/img\/u\/desktop\/prodsliderphoto\/\/hrgpalg_22.jpg?version=58?version=1","https:\/\/i.content4travel.com\/cms\/img\/u\/desktop\/prodsliderphoto\/\/hrgpalg_24.jpg?version=58?version=1","https:\/\/i.content4travel.com\/cms\/img\/u\/desktop\/prodsliderphoto\/\/hrgpalg_25.jpg?version=58?version=1","https:\/\/i.content4travel.com\/cms\/img\/u\/desktop\/prodsliderphoto\/\/hrgpalg_29.jpg?version=58?version=1","https:\/\/i.content4travel.com\/cms\/img\/u\/desktop\/prodsliderphoto\/\/hrgpalg_30.jpg?version=58?version=1","https:\/\/i.content4travel.com\/cms\/img\/u\/desktop\/prodsliderphoto\/\/hrgpalg_31.jpg?version=58?version=1","https:\/\/i.content4travel.com\/cms\/img\/u\/desktop\/prodsliderphoto\/\/hrgpalg_32.jpg?version=58?version=1","https:\/\/i.content4travel.com\/cms\/img\/u\/desktop\/prodsliderphoto\/\/hrgpalg_33.jpg?version=58?version=1","https:\/\/i.content4travel.com\/cms\/img\/u\/desktop\/prodsliderphoto\/\/hrgpalg_34.jpg?version=58?version=1","https:\/\/i.content4travel.com\/cms\/img\/u\/desktop\/prodsliderphoto\/\/hrgpalg_35.jpg?version=58?version=1","https:\/\/i.content4travel.com\/cms\/img\/u\/desktop\/prodsliderphoto\/\/hrgpalg_37.jpg?version=58?version=1","https:\/\/i.content4travel.com\/cms\/img\/u\/desktop\/prodsliderphoto\/\/hrgpalg_40.jpg?version=58?version=1","https:\/\/i.content4travel.com\/cms\/img\/u\/desktop\/prodsliderphoto\/\/hrgpalg_42.jpg?version=58?version=1","https:\/\/i.content4travel.com\/cms\/img\/u\/desktop\/prodsliderphoto\/\/hrgpalg_43.jpg?version=58?version=1","https:\/\/i.content4travel.com\/cms\/img\/u\/desktop\/prodsliderphoto\/\/hrgpalg_44.jpg?version=58?version=1","https:\/\/i.content4travel.com\/cms\/img\/u\/desktop\/prodsliderphoto\/\/hrgpalg_45.jpg?version=58?version=1","https:\/\/i.content4travel.com\/cms\/img\/u\/desktop\/prodsliderphoto\/\/hrgpalg_47.jpg?version=58?version=1","https:\/\/i.content4travel.com\/cms\/img\/u\/desktop\/prodsliderphoto\/\/hrgpalg_48.jpg?version=58?version=1","https:\/\/i.content4travel.com\/cms\/img\/u\/desktop\/prodsliderphoto\/\/hrgpalg_49.jpg?version=58?version=1","https:\/\/i.content4travel.com\/cms\/img\/u\/desktop\/prodsliderphoto\/\/hrgpalg_50.jpg?version=58?version=1","https:\/\/i.content4travel.com\/cms\/img\/u\/desktop\/prodsliderphoto\/\/hrgpalg_52.jpg?version=58?version=1","https:\/\/i.content4travel.com\/cms\/img\/u\/desktop\/prodsliderphoto\/\/hrgpalg_53.jpg?version=58?version=1","https:\/\/i.content4travel.com\/cms\/img\/u\/desktop\/prodsliderphoto\/\/hrgpalg_54.jpg?version=58?version=1","https:\/\/i.content4travel.com\/cms\/img\/u\/desktop\/prodsliderphoto\/\/hrgpalg_55.jpg?version=58?version=1"],"category_name":"itaka","_wc_average_rating":"5.6","stars":5,"_sku":"HRGPALG","adults":3,"childs":4,"rooms":{"DHS":"Pok\u00f3j superior 2 os.","DSV":"Pok\u00f3j superior 2 os. w\/morze","FA2":"Pok\u00f3j rodzinny 2 os."},"foods":{"A":"\u0412\u0441\u0435 \u0432\u043a\u043b\u044e\u0447\u0435\u043d\u043e"},"city-of-departure":{"GDN":"Gda\u0144sk","KTW":"Katowice","POZ":"Pozna\u0144","WAW":"Warszawa","WRO":"Wroc\u0142aw"},"country":"\u0415\u0433\u0438\u043f\u0435\u0442 &#92; \u0425\u0443\u0440\u0433\u0430\u0434\u0430","region":"","terms_and_prices":{"9b56f90f69809aeaa62237ef4ed2eee94c8473786237e1358dbabdb6d6c93ce3":"13.12.2018-27.12.2018","262acc08403e59db276473b0efe0b81875089a4a11e70a72998ca41b0f0266a9":"13.12.2018-20.12.2018","910564876d9d615610c6de094457d9960bcd9517dcaf9596c4bce56fc37ac629":"17.12.2018-24.12.2018","9b56f90f69809aeaa62237ef4ed2eee90accd501d2ea24c93815ecab393889f2":"20.12.2018-27.12.2018","9b56f90f69809aeaa62237ef4ed2eee9e271f1f854172d94d29cdaac3f12f9d4":"03.01.2019-14.01.2019","9b56f90f69809aeaa62237ef4ed2eee943279269f1c427d7b8f9fdeadc1bfdd6":"03.01.2019-17.01.2019","9b56f90f69809aeaa62237ef4ed2eee949c676d4682baa45e9173b249e297dc7":"03.01.2019-10.01.2019","9b56f90f69809aeaa62237ef4ed2eee90c4b4d489d3a4ab876c79f2b7c49d50b":"07.01.2019-17.01.2019","9b56f90f69809aeaa62237ef4ed2eee95e20b7f0ecb2b0749abf799160bb319e":"07.01.2019-21.01.2019","9b56f90f69809aeaa62237ef4ed2eee901c80f65199bc0ebe0b29bd0301d8981":"07.01.2019-14.01.2019","9b56f90f69809aeaa62237ef4ed2eee9b5aa7f311be9349e5f1db820bb8a6494":"10.01.2019-21.01.2019","9b56f90f69809aeaa62237ef4ed2eee9e4b5e62c2adbea71cea386635729dc2c":"10.01.2019-24.01.2019","9b56f90f69809aeaa62237ef4ed2eee941916d599b9d4a7cef524c6e6d7747cc":"10.01.2019-17.01.2019","9b56f90f69809aeaa62237ef4ed2eee93482e7035482b0b6dc24e977da0d8e5e":"14.01.2019-28.01.2019","9b56f90f69809aeaa62237ef4ed2eee991e6157ff2bfb1f87a7965c4786d8903":"14.01.2019-21.01.2019","9b56f90f69809aeaa62237ef4ed2eee91d4981f043f27d24e5b47446b2b7d280":"17.01.2019-28.01.2019","9b56f90f69809aeaa62237ef4ed2eee9caa3df5fae281d86bb19ab9e9e1e6454":"17.01.2019-31.01.2019","9b56f90f69809aeaa62237ef4ed2eee9eb0539d83e223abdf4f19efaa139d232":"17.01.2019-24.01.2019","9b56f90f69809aeaa62237ef4ed2eee995a8a38a50ccc6c05cf1d506cdeec13f":"21.01.2019-31.01.2019","9b56f90f69809aeaa62237ef4ed2eee9bd594d0f7402cd8d8a07eaa4b7a47a6b":"21.01.2019-04.02.2019","9b56f90f69809aeaa62237ef4ed2eee98359e7c4176e57e582a90d72f3c07eab":"21.01.2019-28.01.2019","9b56f90f69809aeaa62237ef4ed2eee9a3043c152ef099928ce76ea16418f3aa":"24.01.2019-04.02.2019","9b56f90f69809aeaa62237ef4ed2eee954413aa516d61bb5633fe607180a7407":"24.01.2019-07.02.2019","9b56f90f69809aeaa62237ef4ed2eee9b63dbef46b4f848192cb796285eb1b30":"24.01.2019-31.01.2019","9b56f90f69809aeaa62237ef4ed2eee903e7fa0deefe950426e6d9a59f0064e8":"28.01.2019-07.02.2019","9b56f90f69809aeaa62237ef4ed2eee92f7d3b85f8a3b545f4c0a2dd09c200e0":"28.01.2019-11.02.2019","9b56f90f69809aeaa62237ef4ed2eee96dda2ff7629390ca3818a1eb119ed8bb":"28.01.2019-04.02.2019","9b56f90f69809aeaa62237ef4ed2eee906875eaaf56784e76a8ffe3cc9fedf04":"31.01.2019-11.02.2019","9b56f90f69809aeaa62237ef4ed2eee98203c0623fc9d8f29838eb3bc5f1ec8d":"31.01.2019-14.02.2019","9b56f90f69809aeaa62237ef4ed2eee9cb926b09e1e1cff3549949037379b041":"31.01.2019-07.02.2019","9b56f90f69809aeaa62237ef4ed2eee9a783dcdf11fdd317f0783eba563565e5":"04.02.2019-14.02.2019","9b56f90f69809aeaa62237ef4ed2eee9de7913dd414bf098f3bd40a8697b12d5":"04.02.2019-18.02.2019","9b56f90f69809aeaa62237ef4ed2eee95aa574e198e2dbc027fd6ceeaac9dd76":"04.02.2019-11.02.2019","9b56f90f69809aeaa62237ef4ed2eee9b09f80c0ae04c3c520c75e0fff77a1f6":"07.02.2019-18.02.2019","9b56f90f69809aeaa62237ef4ed2eee960887c3d19eff6d9899e6d8c5c5563f8":"07.02.2019-21.02.2019","9b56f90f69809aeaa62237ef4ed2eee9bd307924d0b528e1da41d78fbbaae037":"07.02.2019-14.02.2019","9b56f90f69809aeaa62237ef4ed2eee96ac6239b454cfe9280b41683099d35c7":"11.02.2019-18.02.2019","9b56f90f69809aeaa62237ef4ed2eee9bd0760ec2e6727c4b93c9e42dec8a8d6":"14.02.2019-28.02.2019","9b56f90f69809aeaa62237ef4ed2eee987930af64b39144e087b3cff31d76f47":"14.02.2019-21.02.2019","9b56f90f69809aeaa62237ef4ed2eee9b6941ec54c8bb3444d5aebd6d2f8ce0b":"18.02.2019-28.02.2019","9b56f90f69809aeaa62237ef4ed2eee9f5ef28ed5dc166a5f090c7f88c2148d9":"18.02.2019-04.03.2019","9b56f90f69809aeaa62237ef4ed2eee9b00d4ac40375289c8a6e6f2f3df2362e":"18.02.2019-25.02.2019","9b56f90f69809aeaa62237ef4ed2eee91b3469aa7929001db2c6b72eab1673da":"21.02.2019-04.03.2019","9b56f90f69809aeaa62237ef4ed2eee90fed8bde1feed2e5fc5721b83f1eee3c":"21.02.2019-07.03.2019","9b56f90f69809aeaa62237ef4ed2eee9ec0b4a484e9a419dc46bd9d80809a006":"21.02.2019-28.02.2019","9b56f90f69809aeaa62237ef4ed2eee9f00bd30e1f58ca3d598d475af8a0e8c3":"25.02.2019-07.03.2019","9b56f90f69809aeaa62237ef4ed2eee9ff4fa769d4e16d2afb5ed58e98dfb900":"25.02.2019-11.03.2019","9b56f90f69809aeaa62237ef4ed2eee923d690bf61b50fbb2493ca362e1d8ec3":"25.02.2019-04.03.2019","9b56f90f69809aeaa62237ef4ed2eee9c749723a5124717e66d679d03f0fc885":"28.02.2019-11.03.2019","9b56f90f69809aeaa62237ef4ed2eee955c8f8976cd4d6c81f035a0f85a687ec":"28.02.2019-14.03.2019","9b56f90f69809aeaa62237ef4ed2eee9e54396658f7092eaa0d2d2b5017da1ce":"28.02.2019-07.03.2019","9b56f90f69809aeaa62237ef4ed2eee9bc9f35572702da2570acafa0b386d6d4":"04.03.2019-14.03.2019","9b56f90f69809aeaa62237ef4ed2eee9d7be6e1a06f69bf476080d95eb886f60":"04.03.2019-18.03.2019","9b56f90f69809aeaa62237ef4ed2eee932b3ddff488a183016642319bac6e24c":"04.03.2019-11.03.2019","9b56f90f69809aeaa62237ef4ed2eee957782de8c8579e71e8b72888529771d4":"07.03.2019-18.03.2019","9b56f90f69809aeaa62237ef4ed2eee9d77ebdfed6cc94e533eac1c0ac53351e":"07.03.2019-21.03.2019","9b56f90f69809aeaa62237ef4ed2eee91264a77c99d3191775185b3f32091984":"07.03.2019-14.03.2019","9b56f90f69809aeaa62237ef4ed2eee94d4a6b560d6220833aa2f7609f1df368":"11.03.2019-21.03.2019","9b56f90f69809aeaa62237ef4ed2eee972517b39b10a77a7e967dfa6b8ca7056":"11.03.2019-25.03.2019","9b56f90f69809aeaa62237ef4ed2eee9b43ab0102381b51c6f0d1d3450dd152d":"11.03.2019-18.03.2019","9b56f90f69809aeaa62237ef4ed2eee9a36fc9a4afeb6e22d6e4deb07df3a4ea":"14.03.2019-25.03.2019","9b56f90f69809aeaa62237ef4ed2eee9477b756fc6fbcb6700884914c303da85":"14.03.2019-28.03.2019","9b56f90f69809aeaa62237ef4ed2eee91e455ef26a47bf2cd4ab72a51610e82b":"14.03.2019-21.03.2019","9b56f90f69809aeaa62237ef4ed2eee9ae29e81070bc2051e9a5685afaf82920":"18.03.2019-28.03.2019","9b56f90f69809aeaa62237ef4ed2eee9004aa7ce4ff52597823c1c223fb13bb7":"18.03.2019-01.04.2019","9b56f90f69809aeaa62237ef4ed2eee961e7d43c2a605a50b0696736e893e3e6":"18.03.2019-25.03.2019","9b56f90f69809aeaa62237ef4ed2eee936e1042785e2b6806185d090a4c0f088":"21.03.2019-01.04.2019","9b56f90f69809aeaa62237ef4ed2eee9f4f1b11c3d1df39652d331d091caa89d":"21.03.2019-04.04.2019","9b56f90f69809aeaa62237ef4ed2eee9357ad0d62e9954e2af5f06cbc0ad6ce1":"21.03.2019-28.03.2019","9b56f90f69809aeaa62237ef4ed2eee95c1ebefaf8a4d66420c832ca0d25fd26":"25.03.2019-04.04.2019","9b56f90f69809aeaa62237ef4ed2eee96175f4271fcdc4a0b9b30583eb957c2f":"25.03.2019-08.04.2019","9b56f90f69809aeaa62237ef4ed2eee97312a5004af99f57709423373209b137":"25.03.2019-01.04.2019","9b56f90f69809aeaa62237ef4ed2eee95ef3c882010c782c32d826ef75f9a1b6":"28.03.2019-08.04.2019","9b56f90f69809aeaa62237ef4ed2eee965948b921ec7b415ba00a4fc88e9def2":"28.03.2019-11.04.2019","9b56f90f69809aeaa62237ef4ed2eee9dd62f06c359073b0ff4a02e9064e74c4":"28.03.2019-04.04.2019","db53f18b381c26c7459dc3f9bbf8c567b75f7fd7aceeadd54d38a2aefba09049":"01.04.2019-11.04.2019","db53f18b381c26c7459dc3f9bbf8c56725a763a10cc1533831f38c25057c865a":"01.04.2019-15.04.2019","db53f18b381c26c7459dc3f9bbf8c56706d98ccccdd8640be91d169647d13107":"01.04.2019-08.04.2019","db53f18b381c26c7459dc3f9bbf8c567ea3ba3967e0499ebbafe3cc1c796d007":"04.04.2019-15.04.2019","db53f18b381c26c7459dc3f9bbf8c56729023e02df696d499e51f310a19f7e35":"04.04.2019-18.04.2019","db53f18b381c26c7459dc3f9bbf8c56740b92f332bc8c4dc9e57abd037fbfde3":"04.04.2019-11.04.2019","db53f18b381c26c7459dc3f9bbf8c56703e75600bf24d68ca000bbb5dd5a0e2c":"08.04.2019-18.04.2019","db53f18b381c26c7459dc3f9bbf8c567988c0633021dd8420b32aa9ceacac197":"08.04.2019-22.04.2019","db53f18b381c26c7459dc3f9bbf8c567d24a0bfcec1a810fb93c8519ab0cab64":"08.04.2019-15.04.2019","db53f18b381c26c7459dc3f9bbf8c567b621e6e72216b0912a5a545207f75a21":"11.04.2019-22.04.2019","db53f18b381c26c7459dc3f9bbf8c567b93604abe7f464a6255addfeda345851":"11.04.2019-25.04.2019","db53f18b381c26c7459dc3f9bbf8c567e359dfa018d8bf9e33e9aa3f5e599ce8":"11.04.2019-18.04.2019","db53f18b381c26c7459dc3f9bbf8c5672d3fc592d4babdb945eadde443bfb777":"15.04.2019-25.04.2019","db53f18b381c26c7459dc3f9bbf8c5670daaa9fe3825c978f3b98a6563bacf4e":"15.04.2019-22.04.2019","db53f18b381c26c7459dc3f9bbf8c567fa26bac8d3b4314f27d9d19d54e5e9b8":"18.04.2019-29.04.2019","db53f18b381c26c7459dc3f9bbf8c5676698f87d77e6804c285c9249e9a47cdb":"18.04.2019-02.05.2019","db53f18b381c26c7459dc3f9bbf8c567e94d4e0268eeb357de58ab86e5ddcc8b":"18.04.2019-25.04.2019","db53f18b381c26c7459dc3f9bbf8c5672de12de9bfb38887ad63d39ae58f5f2c":"22.04.2019-02.05.2019","db53f18b381c26c7459dc3f9bbf8c567e542ebcb267e1a8991273a50928ded03":"25.04.2019-06.05.2019","db53f18b381c26c7459dc3f9bbf8c56761aed34c56570668e25404cf98c99789":"25.04.2019-09.05.2019","db53f18b381c26c7459dc3f9bbf8c56751bbca5d9f22710532a52fc7883c9fbe":"25.04.2019-02.05.2019","db53f18b381c26c7459dc3f9bbf8c56784a6b495789f5d87d6f3c8957902600d":"29.04.2019-09.05.2019","db53f18b381c26c7459dc3f9bbf8c5672947b1c4e9a8707e9eac2ff325ee45e8":"29.04.2019-13.05.2019","db53f18b381c26c7459dc3f9bbf8c567735643d05f70fcc3eca56f5880b0042e":"29.04.2019-06.05.2019","db53f18b381c26c7459dc3f9bbf8c5674ff2e7ae17cdb740df943b61efadc09e":"02.05.2019-13.05.2019","db53f18b381c26c7459dc3f9bbf8c56788f4a7baceff05665f0e5f88707170ce":"02.05.2019-16.05.2019","db53f18b381c26c7459dc3f9bbf8c567cb21a46a31ec2c673886e751e80a721f":"02.05.2019-09.05.2019","db53f18b381c26c7459dc3f9bbf8c567d49ea3e269d715ec0adfc854b1f70175":"06.05.2019-16.05.2019","db53f18b381c26c7459dc3f9bbf8c5674b68fb44b0c8b20a02f111a6540c339a":"06.05.2019-20.05.2019","db53f18b381c26c7459dc3f9bbf8c56776895a2c5deb3209cd21c0ca94fbc069":"06.05.2019-13.05.2019","db53f18b381c26c7459dc3f9bbf8c5672a5ea35527a0e9c8094cc00c7efa1dd0":"09.05.2019-20.05.2019","db53f18b381c26c7459dc3f9bbf8c5675f9d5317fbe1c0d26cd8bf4d44bbf3fa":"09.05.2019-23.05.2019","db53f18b381c26c7459dc3f9bbf8c567bec2d28dd1b69bf1a547e17f3524f25b":"09.05.2019-16.05.2019","db53f18b381c26c7459dc3f9bbf8c567c418f368df4b0bde16a576d04bcb3172":"13.05.2019-23.05.2019","db53f18b381c26c7459dc3f9bbf8c5679726e232fb8c436ecc4d5a447c829a51":"13.05.2019-27.05.2019","db53f18b381c26c7459dc3f9bbf8c567b3874e9b35cc076d7fe6fc9e0316c804":"13.05.2019-20.05.2019","db53f18b381c26c7459dc3f9bbf8c5677e42d2a61f65b6fb26876eb3ebe0c2e0":"16.05.2019-27.05.2019","db53f18b381c26c7459dc3f9bbf8c567db79b06c7fd57e7acd7bec987427c515":"16.05.2019-30.05.2019","db53f18b381c26c7459dc3f9bbf8c5675d0b68a2cdcdf4384cf930870fc28e9d":"16.05.2019-23.05.2019","db53f18b381c26c7459dc3f9bbf8c567a7ef784a78bc45567497b8df97c39e69":"20.05.2019-30.05.2019","db53f18b381c26c7459dc3f9bbf8c56773af6629902305d6b5d0ae7e394aa424":"20.05.2019-03.06.2019","db53f18b381c26c7459dc3f9bbf8c567bd7d38b9a1e7be3642737556a2079837":"20.05.2019-27.05.2019","db53f18b381c26c7459dc3f9bbf8c56778945a085da6674c6fccd523c31e3799":"23.05.2019-03.06.2019","db53f18b381c26c7459dc3f9bbf8c567aa535acadd7042d06b9c6bb99b905b99":"23.05.2019-06.06.2019","db53f18b381c26c7459dc3f9bbf8c5670b1d846948a1c47ce7e15518ea2deb2a":"23.05.2019-30.05.2019","db53f18b381c26c7459dc3f9bbf8c5673b734c4f540f19bc4b5ad669da236850":"27.05.2019-06.06.2019","db53f18b381c26c7459dc3f9bbf8c567268e7a93c2ab3d4f0041474b1c584664":"27.05.2019-10.06.2019","db53f18b381c26c7459dc3f9bbf8c5676f391f82259aab5ebdfcb60650f0d61a":"27.05.2019-03.06.2019","db53f18b381c26c7459dc3f9bbf8c56718d48c72f0fb43fbe6caea52ce395120":"30.05.2019-10.06.2019","db53f18b381c26c7459dc3f9bbf8c5673a80e7e3d278f0fee5daa474e47bc312":"30.05.2019-13.06.2019","db53f18b381c26c7459dc3f9bbf8c567610462e1caea03b3d1b04f8cb6d210d3":"30.05.2019-06.06.2019","db53f18b381c26c7459dc3f9bbf8c567fd348dc14dcea07ecab0cf178f2753d5":"03.06.2019-13.06.2019","db53f18b381c26c7459dc3f9bbf8c567d96b8dad24e1a7d7412409cc40054933":"03.06.2019-17.06.2019","db53f18b381c26c7459dc3f9bbf8c567dc4a1991107208875d47ac5b96cd5092":"03.06.2019-10.06.2019","db53f18b381c26c7459dc3f9bbf8c567abb77da2d4a7fd74d7e3186d250ed0c9":"06.06.2019-17.06.2019","db53f18b381c26c7459dc3f9bbf8c567eb509677753555cc605ee8c5c1de6ff0":"06.06.2019-20.06.2019","db53f18b381c26c7459dc3f9bbf8c567a07165f9f81829b7f485fd278ff594de":"06.06.2019-13.06.2019","db53f18b381c26c7459dc3f9bbf8c5671acd943ba1f498486a1c7a2811bf3bcc":"10.06.2019-20.06.2019","db53f18b381c26c7459dc3f9bbf8c56763e968a3584975ff409c73c4b331650d":"10.06.2019-24.06.2019","db53f18b381c26c7459dc3f9bbf8c567c680733f0884e1046e7b1a69d309139e":"10.06.2019-17.06.2019","db53f18b381c26c7459dc3f9bbf8c567f6bc9b73c641037cbd581373e122d877":"13.06.2019-24.06.2019","db53f18b381c26c7459dc3f9bbf8c5673ac3b27edfe8791ff716f055594206fd":"13.06.2019-27.06.2019","db53f18b381c26c7459dc3f9bbf8c5672d2dba85bfd05bdfe0f83b3a71259fa2":"13.06.2019-20.06.2019","db53f18b381c26c7459dc3f9bbf8c567030a8feab77ec3c89e0719fae104bbe2":"17.06.2019-27.06.2019","db53f18b381c26c7459dc3f9bbf8c567263d4973e00224105661f9d52b4a601e":"17.06.2019-01.07.2019","db53f18b381c26c7459dc3f9bbf8c5676f02b6611cdbab3e4dcf4550ef1ff19a":"17.06.2019-24.06.2019","db53f18b381c26c7459dc3f9bbf8c567bacc3594246d496f558d7718e989018a":"20.06.2019-01.07.2019","db53f18b381c26c7459dc3f9bbf8c56730041aac3b4cafad27b57add1625b27d":"20.06.2019-04.07.2019","db53f18b381c26c7459dc3f9bbf8c567ec30fed398fa8d77a60876dd52046c91":"20.06.2019-27.06.2019","db53f18b381c26c7459dc3f9bbf8c5677a866d604a8b835fb2c6180bd4d7c934":"24.06.2019-08.07.2019","db53f18b381c26c7459dc3f9bbf8c567f0ff456ead8529863217eea1cffc5944":"24.06.2019-01.07.2019","db53f18b381c26c7459dc3f9bbf8c567aa539bc486a7148136deeda7174f0476":"27.06.2019-08.07.2019","db53f18b381c26c7459dc3f9bbf8c5678d56d444f77a228fe3516875a04839ee":"27.06.2019-11.07.2019","db53f18b381c26c7459dc3f9bbf8c5674ddf2cbf5be4907005a9a5baa18e15a2":"27.06.2019-04.07.2019","db53f18b381c26c7459dc3f9bbf8c5674810aadb0efcf8fbf2c372f30aea3b93":"01.07.2019-11.07.2019","db53f18b381c26c7459dc3f9bbf8c56702e040a55b83d47fe6996a53d7c96f77":"01.07.2019-15.07.2019","db53f18b381c26c7459dc3f9bbf8c567e8a39a4134d29d5d1609cf5ae52e891c":"01.07.2019-08.07.2019","db53f18b381c26c7459dc3f9bbf8c5673eb6c20c34160ea33cb68d72a5077953":"04.07.2019-15.07.2019","db53f18b381c26c7459dc3f9bbf8c567abf7b87acd7eb9d10265504770061d19":"04.07.2019-18.07.2019","db53f18b381c26c7459dc3f9bbf8c567a885bb451bff44445548c4a19d4db8d5":"04.07.2019-11.07.2019","db53f18b381c26c7459dc3f9bbf8c5673eb65c724882df7c3f8110762a789c09":"08.07.2019-18.07.2019","db53f18b381c26c7459dc3f9bbf8c56718bcfb652845074c09d64dff2ee3f066":"08.07.2019-22.07.2019","db53f18b381c26c7459dc3f9bbf8c5672329e97fa53df2bb4ba12f9009fee069":"08.07.2019-15.07.2019","db53f18b381c26c7459dc3f9bbf8c5674bd24f15e776c8077888bdcff5c4a2a6":"11.07.2019-22.07.2019","db53f18b381c26c7459dc3f9bbf8c567032fb7256452e971859e0792044cf0ad":"11.07.2019-25.07.2019","db53f18b381c26c7459dc3f9bbf8c5676804efeb0c485056f39139dc54d796f6":"11.07.2019-18.07.2019","db53f18b381c26c7459dc3f9bbf8c567a46c137b43f0da0abdda55b5e1658687":"15.07.2019-25.07.2019","db53f18b381c26c7459dc3f9bbf8c567b8a01954d89106c8351822165728481b":"15.07.2019-29.07.2019","db53f18b381c26c7459dc3f9bbf8c5674dd70e02e6e2924135983fd2f1e091c9":"15.07.2019-22.07.2019","db53f18b381c26c7459dc3f9bbf8c5679144403dfd70826641161b22c87ef84f":"18.07.2019-29.07.2019","db53f18b381c26c7459dc3f9bbf8c5670cefc1cefc6a23bbf12628bd9839798c":"18.07.2019-01.08.2019","db53f18b381c26c7459dc3f9bbf8c567092c0b43e9795b05bf9fdb2cdd413828":"18.07.2019-25.07.2019","db53f18b381c26c7459dc3f9bbf8c567ae0620afb8d2046d0aa89d5b1f594c22":"22.07.2019-01.08.2019","db53f18b381c26c7459dc3f9bbf8c5674a525f1b6d642e1d3aa34efc803c1323":"22.07.2019-05.08.2019","db53f18b381c26c7459dc3f9bbf8c567a24d7c62025b1c4f7eac847c45100ea3":"22.07.2019-29.07.2019","db53f18b381c26c7459dc3f9bbf8c567e18f882b1a5da1931941008f08046b81":"25.07.2019-05.08.2019","db53f18b381c26c7459dc3f9bbf8c567f7ee1e24d5aeb589f809e4ea88452512":"25.07.2019-08.08.2019","db53f18b381c26c7459dc3f9bbf8c5677ca7b12805451d88ca8d7cb644e4430b":"25.07.2019-01.08.2019","db53f18b381c26c7459dc3f9bbf8c567e605d5340c84e3aa56128e56bf4d7d12":"29.07.2019-08.08.2019","db53f18b381c26c7459dc3f9bbf8c5678c54f5957dcf97bda82e5d3403a3d8cd":"29.07.2019-12.08.2019","db53f18b381c26c7459dc3f9bbf8c56793105639572f651974968f51eabd3d26":"29.07.2019-05.08.2019","db53f18b381c26c7459dc3f9bbf8c567bfdf881f1cf63601e6f5a04cf110c667":"01.08.2019-12.08.2019","db53f18b381c26c7459dc3f9bbf8c567c33f663fd846a45c64bb6579b5413736":"01.08.2019-15.08.2019","db53f18b381c26c7459dc3f9bbf8c56706da4781f23b68246bb6c4582e4eef82":"01.08.2019-08.08.2019","db53f18b381c26c7459dc3f9bbf8c567cb776d7db2c081b83729337feaf277f8":"05.08.2019-15.08.2019","db53f18b381c26c7459dc3f9bbf8c5676e824418b994b9ecc0b5d0209d5de83f":"05.08.2019-19.08.2019","db53f18b381c26c7459dc3f9bbf8c567fb5e01759c8cbeb47d63ff8d13c804fb":"05.08.2019-12.08.2019","db53f18b381c26c7459dc3f9bbf8c5679295549a70afdba272f14a711d03bd10":"08.08.2019-19.08.2019","db53f18b381c26c7459dc3f9bbf8c56729a683c3d555d4efcc00d0df23665d1a":"08.08.2019-22.08.2019","db53f18b381c26c7459dc3f9bbf8c567e1b80ff39aa1c96d8b721656170601ec":"08.08.2019-15.08.2019","db53f18b381c26c7459dc3f9bbf8c56750d7756fc00ffcd28e5276841c223984":"12.08.2019-22.08.2019","db53f18b381c26c7459dc3f9bbf8c5676cf65d48ef66d589aa253c49141b3431":"12.08.2019-26.08.2019","db53f18b381c26c7459dc3f9bbf8c567b6a2396cc2021797b55df7dfd7deb711":"12.08.2019-19.08.2019","db53f18b381c26c7459dc3f9bbf8c56727375f6d04120a64e499a48567fb717d":"15.08.2019-26.08.2019","db53f18b381c26c7459dc3f9bbf8c567bf9774f7def182382a459842b91a02f4":"15.08.2019-29.08.2019","db53f18b381c26c7459dc3f9bbf8c567357e2d1e3646c49d4a2258be72c207b3":"15.08.2019-22.08.2019","db53f18b381c26c7459dc3f9bbf8c567289237503e3677a50ed797a90e651041":"19.08.2019-29.08.2019","db53f18b381c26c7459dc3f9bbf8c567776330c5124df82308a4affc1c8757b8":"19.08.2019-02.09.2019","db53f18b381c26c7459dc3f9bbf8c56744a7f2bf5e7bc50357bf15bdb74532e1":"19.08.2019-26.08.2019","db53f18b381c26c7459dc3f9bbf8c56784c7f2bddf60ca80fe2d56adde543ee8":"22.08.2019-02.09.2019","db53f18b381c26c7459dc3f9bbf8c567ff8c35de4a63df2b5f8b7ab0ab400058":"22.08.2019-05.09.2019","db53f18b381c26c7459dc3f9bbf8c567b5984af04ccb5278aaab9434e4a9be93":"22.08.2019-29.08.2019","db53f18b381c26c7459dc3f9bbf8c5671c9d557b2970f2d08835e5ddbd4274c9":"26.08.2019-05.09.2019","db53f18b381c26c7459dc3f9bbf8c567b1c9b9793094cdfc134f8b71ab63f57f":"26.08.2019-09.09.2019","db53f18b381c26c7459dc3f9bbf8c56731fca77a07724fd00b6f84065eb9f0c5":"26.08.2019-02.09.2019","db53f18b381c26c7459dc3f9bbf8c567b18b5e83052fdcb162155c0a679bc491":"29.08.2019-09.09.2019","db53f18b381c26c7459dc3f9bbf8c567c423299c0fbd40e346d01117fbeba5e7":"29.08.2019-12.09.2019","db53f18b381c26c7459dc3f9bbf8c567774bf6011a58b7999439c4ef5c890424":"29.08.2019-05.09.2019","db53f18b381c26c7459dc3f9bbf8c567b4077f577d8ccebc315e1e7da7833f6c":"02.09.2019-12.09.2019","db53f18b381c26c7459dc3f9bbf8c56796fdc1617d443d92caec8aef8f581e9d":"02.09.2019-16.09.2019","db53f18b381c26c7459dc3f9bbf8c5673f6769bf2fff2b6fdfb96fab862f80e6":"02.09.2019-09.09.2019","db53f18b381c26c7459dc3f9bbf8c5675271bf56f2b25f6c97eb358e130b086e":"05.09.2019-16.09.2019","db53f18b381c26c7459dc3f9bbf8c56782057934d5673f89c77d8fe296c9c250":"05.09.2019-19.09.2019","db53f18b381c26c7459dc3f9bbf8c56773983a85971ab3922c9fdc056dd4949e":"05.09.2019-12.09.2019","db53f18b381c26c7459dc3f9bbf8c56771b30cb8fad2a7c3d20d35e5e596582f":"09.09.2019-19.09.2019","db53f18b381c26c7459dc3f9bbf8c567df0169f7b9131e9ce421f54585f3df4c":"09.09.2019-23.09.2019","db53f18b381c26c7459dc3f9bbf8c5671fdae74a6133ec812c4ba4fc7f8238a3":"09.09.2019-16.09.2019","db53f18b381c26c7459dc3f9bbf8c567212346c0c402c586c6495e8275cbf14f":"12.09.2019-23.09.2019","db53f18b381c26c7459dc3f9bbf8c5670ffbb6e67e75fe1c39e2ce33b5ae82c8":"12.09.2019-26.09.2019","db53f18b381c26c7459dc3f9bbf8c56722ff74c79743d89934dd41410fa2a16c":"12.09.2019-19.09.2019","db53f18b381c26c7459dc3f9bbf8c567fc3fd2a98606e0237cab5205d57a3f8f":"16.09.2019-26.09.2019","db53f18b381c26c7459dc3f9bbf8c5679f797a556f8ac900eea0c2caf96c5c2d":"16.09.2019-30.09.2019","db53f18b381c26c7459dc3f9bbf8c567cd93f9f38ec06f6b8a27032cafdc935f":"16.09.2019-23.09.2019","db53f18b381c26c7459dc3f9bbf8c5678bc6bcf1090d8ea933553b828874c780":"19.09.2019-30.09.2019","db53f18b381c26c7459dc3f9bbf8c567cfd71054ebc92042b79b67f1b9604f58":"19.09.2019-03.10.2019","db53f18b381c26c7459dc3f9bbf8c5672c35ce1fd06462b94dfbb8def2c80100":"19.09.2019-26.09.2019","db53f18b381c26c7459dc3f9bbf8c567aad6f5bc80e34606fd0d21ec9584baf8":"23.09.2019-03.10.2019","db53f18b381c26c7459dc3f9bbf8c5670b4eabadeba582b1faaa90042ec62d54":"23.09.2019-07.10.2019","db53f18b381c26c7459dc3f9bbf8c5673b2c461629ce5b3fccd8298b93ffec10":"23.09.2019-30.09.2019","db53f18b381c26c7459dc3f9bbf8c567aabc09a81b9cdddcf4fb593ca523affd":"26.09.2019-07.10.2019","db53f18b381c26c7459dc3f9bbf8c567bbf6a84d3e359aebc20fc6820d70721c":"26.09.2019-10.10.2019","db53f18b381c26c7459dc3f9bbf8c5673ff0ef0754dc54cf5381b4f331444213":"26.09.2019-03.10.2019","db53f18b381c26c7459dc3f9bbf8c5676b17913102af5548de576931e09a8acb":"30.09.2019-10.10.2019","db53f18b381c26c7459dc3f9bbf8c56714ab268365510211e69b46fff3e8d33e":"30.09.2019-14.10.2019","db53f18b381c26c7459dc3f9bbf8c56700590f530392aea446750bb4a696bf60":"30.09.2019-07.10.2019","db53f18b381c26c7459dc3f9bbf8c5677d5b6a84ddfa49fb6a78fcaecd829197":"03.10.2019-14.10.2019","db53f18b381c26c7459dc3f9bbf8c567e79bae50f2d9e192d7ea8a0d8951fa31":"03.10.2019-17.10.2019","db53f18b381c26c7459dc3f9bbf8c567c26782026f84de58546da4e47e4d332d":"03.10.2019-10.10.2019","db53f18b381c26c7459dc3f9bbf8c567e23b6519bcefa62a5c390ba9e56627b0":"07.10.2019-17.10.2019","db53f18b381c26c7459dc3f9bbf8c567b6e2f347ce5a1659827f10e85c37402a":"07.10.2019-21.10.2019","db53f18b381c26c7459dc3f9bbf8c56752c0cc964398c28b3140bef8865ce492":"07.10.2019-14.10.2019","db53f18b381c26c7459dc3f9bbf8c567ede8df18d9d0d272735d29a9b206c928":"10.10.2019-21.10.2019","db53f18b381c26c7459dc3f9bbf8c567591aed88908b9ccf0c80cc948190792b":"10.10.2019-24.10.2019","db53f18b381c26c7459dc3f9bbf8c567d25dc63d09f84b4c206c5d8fd3a68a8d":"10.10.2019-17.10.2019","db53f18b381c26c7459dc3f9bbf8c56786445e5c3bb418451e94c1242c1fd06b":"14.10.2019-24.10.2019","db53f18b381c26c7459dc3f9bbf8c567a6c29ab6047358563460681a12be4f64":"14.10.2019-28.10.2019","db53f18b381c26c7459dc3f9bbf8c567f7385712630c51319b426886a7bf05c5":"14.10.2019-21.10.2019","db53f18b381c26c7459dc3f9bbf8c56784b4d111b3723b7e88d4210a2f4ecea3":"17.10.2019-28.10.2019","db53f18b381c26c7459dc3f9bbf8c567ce8125f6863308941f7668d73b8ce7d9":"17.10.2019-31.10.2019","db53f18b381c26c7459dc3f9bbf8c56726cd6e61fbd16f253f7efacb1427f5be":"17.10.2019-24.10.2019","db53f18b381c26c7459dc3f9bbf8c56757aed1be63e960a9fea923ec507bc319":"21.10.2019-31.10.2019","db53f18b381c26c7459dc3f9bbf8c567e8200ec95e9609ae51125270357e9a7a":"21.10.2019-28.10.2019","db53f18b381c26c7459dc3f9bbf8c5673bc9792e39d8f55f0c0997b553887e3e":"24.10.2019-31.10.2019"},"_regular_price":"70433","_sale_price":"42896","percent_rating":"100%","child_price_6":0,"child_price_13":0,"bus_tour":"\u041d\u0435\u0442","post_title":"Hotel Sentido Palm Royal","post_excerpt":"\u044d\u043b\u0435\u0433\u0430\u043d\u0442\u043d\u044b\u0435 \u0438 \u0441\u0442\u0438\u043b\u044c\u043d\u044b\u0435 \u0438\u043d\u0442\u0435\u0440\u044c\u0435\u0440\u044b\r\n\u043e\u0442\u043b\u0438\u0447\u043d\u043e\u0435 \u043e\u0431\u0441\u043b\u0443\u0436\u0438\u0432\u0430\u043d\u0438\u0435\r\n\u043f\u0440\u0435\u0432\u043e\u0441\u0445\u043e\u0434\u043d\u0430\u044f \u0438\u043d\u0442\u0435\u0440\u043d\u0430\u0446\u0438\u043e\u043d\u0430\u043b\u044c\u043d\u0430\u044f \u043a\u0443\u0445\u043d\u044f\r\n\u0438\u0434\u0435\u0430\u043b\u044c\u043d\u044b\u0435 \u0443\u0441\u043b\u043e\u0432\u0438\u044f \u0434\u043b\u044f \u0437\u0430\u043d\u044f\u0442\u0438\u044f \u0432\u043e\u0434\u043d\u044b\u043c\u0438 \u0432\u0438\u0434\u0430\u043c\u0438 \u0441\u043f\u043e\u0440\u0442\u0430","post_content":"<div class=\"product-productdescription\"> <p><strong data-block-type=\"raspolozhenie\">\u0420\u0410\u0421\u041f\u041e\u041b\u041e\u0416\u0415\u041d\u0418\u0415: <\/strong> \u0432 \u043a\u0432\u0430\u0440\u0442\u0430\u043b\u0435 Soma Bay, o\u043a. 12 \u043a\u043c \u043e\u0442 \u0421\u0430\u0444\u0430\u0433\u0438, o\u043a. 40 \u043a\u043c \u043e\u0442 \u0425\u0423\u0420\u0413\u0410\u0414\u042b; o\u043a. 45 \u043a\u043c \u043e\u0442 \u0430\u044d\u0440\u043e\u043f\u043e\u0440\u0442\u0430 \u0432 \u0425\u0443\u0440\u0433\u0430\u0434\u0435; \u0441\u0431\u043e\u0440\u043d\u044b\u0439 \u0442\u0440\u0430\u043d\u0441\u0444\u0435\u0440 (\u0430\u044d\u0440\u043e\u043f\u043e\u0440\u0442-\u043e\u0442\u043b\u0435\u044c-\u0430\u044d\u0440\u043e\u043f\u043e\u0440\u0442) \u0432\u043a\u043b\u044e\u0447\u0435\u043d \u0432 \u0441\u0442\u043e\u0438\u043c\u043e\u0441\u0442\u044c, \u0434\u043b\u044f \u0436\u0435\u043b\u0430\u044e\u0449\u0438\u0445 \u0438\u043d\u0434\u0438\u0432\u0438\u0434\u0443\u0430\u043b\u044c\u043d\u044b\u0439 \u0442\u0440\u0430\u043d\u0441\u0444\u0435\u0440 \u043f\u043e \u0437\u0430\u043a\u0430\u0437\u0443 (\u043c\u0438\u043d. 2 \u0432\u0437\u0440\u043e\u0441\u043b\u044b\u0445): 149 PLN\/\u0442\u0443\u0434\u0430 \u0438 \u043e\u0431\u0440\u0430\u0442\u043d\u043e (\u0430\u044d\u0440\u043e\u043f\u043e\u0440\u0442-\u043e\u0442\u0435\u043b\u044c-\u0430\u044d\u0440\u043e\u043f\u043e\u0440\u0442)\/\u0432\u0437\u0440\u043e\u0441\u043b\u044b\u0439, \u0440\u0435\u0431\u0435\u043d\u043e\u043a \u0441\u0442\u0430\u0440\u0448\u0435 2 \u043b\u0435\u0442; \u0434\u0435\u0442\u0438 \u0434\u043e 2 \u043b\u0435\u0442 \u2013 \u0431\u0435\u0441\u043f\u043b\u0430\u0442\u043d\u043e.<\/p><p><strong data-block-type=\"plyazh\">\u041f\u041b\u042f\u0416: <\/strong> \u043e\u0442\u0435\u043b\u044c\u043d\u044b\u0439, \u043f\u0435\u0441\u0447\u0430\u043d\u044b\u0439, \u0434\u043b\u0438\u043d\u043e\u0439 (\u043e\u043a. 1,2 \u043a\u043c), \u043f\u043e\u043b\u043e\u0433\u0438\u0439 \u0441\u043f\u0443\u0441\u043a \u043a \u043c\u043e\u0440\u044e, \u043d\u0435\u043f\u043e\u0441\u0440\u0435\u0434\u0441\u0442\u0432\u0435\u043d\u043d\u043e \u0443 \u043e\u0442\u0435\u043b\u044f, \u0431\u0435\u0441\u043f\u043b\u0430\u0442\u043d\u044b\u0435 \u0437\u043e\u043d\u0442\u044b, \u0448\u0435\u0437\u043b\u043e\u043d\u0433\u0438, \u043c\u0430\u0442\u0440\u0430\u0446\u044b \u0438 \u043f\u043e\u043b\u043e\u0442\u0435\u043d\u0446\u0430; \u0431\u0430\u0440.<\/p><p><strong data-block-type=\"otel\">\u041e\u0422\u0415\u041b\u042c: <\/strong> \u043f\u044f\u0442\u0438\u0437\u0432\u0435\u0437\u0434\u043e\u0447\u043d\u044b\u0439, \u044d\u043b\u0435\u0433\u0430\u043d\u0442\u043d\u044b\u0439 \u0438 \u0441\u0442\u0438\u043b\u044c\u043d\u044b\u0439, \u043f\u043e\u0441\u0442\u0440\u043e\u0435\u043d \u0432 2004 \u0433., \u043e\u0431\u043d\u043e\u0432\u043b\u0435\u043d \u0432 2007 \u0433., 445 \u043d\u043e\u043c\u0435\u0440\u043e\u0432, 3 \u0437\u0434\u0430\u043d\u0438\u044f: \u0433\u043b\u0430\u0432\u043d\u043e\u0435 \u0437\u0434\u0430\u043d\u0438\u0435, 5 \u044d\u0442\u0430\u0436\u0435\u0439 \u0438 2 \u0434\u043e\u043f\u043e\u043b\u043d\u0438\u0442\u0435\u043b\u044c\u043d\u044b\u0435 \u0437\u0434\u0430\u043d\u0438\u044f, 3 \u044d\u0442\u0430\u0436\u0430, 4 \u043b\u0438\u0444\u0442\u0430, \u043f\u0440\u043e\u0441\u0442\u043e\u0440\u043d\u043e\u0435 \u0438 \u044d\u043b\u0435\u0433\u0430\u043d\u0442\u043d\u043e\u0435 \u043b\u043e\u0431\u0431\u0438, \u043a\u0440\u0443\u0433\u043b\u043e\u0441\u0443\u0442\u043e\u0447\u043d\u044b\u0439 \u0440\u0435\u0441\u0435\u043f\u0448\u0435\u043d, \u0433\u043b\u0430\u0432\u043d\u044b\u0439 \u0440\u0435\u0441\u0442\u043e\u0440\u0430\u043d - \u043f\u0438\u0442\u0430\u043d\u0438\u0435, \u0448\u0432\u0435\u0434\u0441\u043a\u0438\u0439 \u0441\u0442\u043e\u043b, \u0438\u043d\u0442\u0435\u0440\u043d\u0430\u0446\u0438\u043e\u043d\u0430\u043b\u044c\u043d\u0430\u044f \u043a\u0443\u0445\u043d\u044f, \u043f\u0440\u0435\u0434\u0443\u0441\u043c\u043e\u0442\u0440\u0435\u043d\u044b \u0434\u0435\u0442\u0441\u043a\u0438\u0435 \u043a\u0440\u0435\u0441\u043b\u0430, \u0432\u0435\u0433\u0435\u0442\u0430\u0440\u0438\u0430\u043d\u0441\u043a\u0438\u0435 \u0431\u043b\u044e\u0434\u0430, 4 \u0440\u0435\u0441\u0442\u043e\u0440\u0430\u043d\u0430 \u00e0 la carte, \u043e\u0431\u0441\u043b\u0443\u0436\u0438\u0432\u0430\u0435\u0442\u0441\u044f \u043e\u0444\u0438\u0446\u0438\u0430\u043d\u0442\u0430\u043c\u0438 (\u043f\u043e \u043f\u0440\u0435\u0434\u0432\u0430\u0440\u0438\u0442\u0435\u043b\u044c\u043d\u043e\u043c\u0443 \u0437\u0430\u043a\u0430\u0437\u0443): \u0430\u0437\u0438\u0430\u0442\u0441\u043a\u0438\u0439, \u0433\u0440\u0435\u0447\u0435\u0441\u043a\u0438\u0439, \u0438\u0442\u0430\u043b\u044c\u044f\u043d\u0441\u043a\u0438\u0439 \u0438 \u043b\u0438\u0432\u0430\u043d\u0441\u043a\u0438\u0439; \u0431\u0430\u0440\u044b: Atrium \u0432 \u043b\u043e\u0431\u0431\u0438, Azur, Cleopatra Disco, Johnny's \u0431\u0430\u0440, Captain Nemo's \u0432\u043e\u0437\u043b\u0435 \u043f\u043b\u044f\u0436\u0430, \u0431\u0430\u0440 \u0442\u0438\u043f\u0430 swim-up, \u0443\u0433\u043e\u043b\u043e\u043a \u0441 \u043a\u0430\u043b\u044c\u044f\u043d\u043e\u043c (\u0437\u0430 \u043e\u0442\u0434\u0435\u043b\u044c\u043d\u0443\u044e \u043f\u043b\u0430\u0442\u0443), \u043f\u0443\u043d\u043a\u0442 \u043e\u0431\u043c\u0435\u043d\u0430 \u0432\u0430\u043b\u044e\u0442, \u0441\u0443\u0432\u0435\u043d\u0438\u0440\u043d\u044b\u0439 \u043c\u0430\u0433\u0430\u0437\u0438\u043d, \u0442\u043e\u0440\u0433\u043e\u0432\u044b\u0439 \u043c\u0438\u043d\u0438-\u0446\u0435\u043d\u0442\u0440; 3 \u043a\u043e\u043d\u0444\u0435\u0440\u0435\u043d\u0446-\u0437\u0430\u043b\u0430, \u0441\u0430\u0434, \u0431\u0435\u0441\u043f\u043b\u0430\u0442\u043d\u044b\u0439 \u0431\u0435\u0441\u043f\u0440\u043e\u0432\u043e\u0434\u043d\u043e\u0439 \u0418\u043d\u0442\u0435\u0440\u043d\u0435\u0442; \u0437\u0430 \u043e\u0442\u0434\u0435\u043b\u044c\u043d\u0443\u044e \u043f\u043b\u0430\u0442\u0443: \u043e\u0431\u0441\u043b\u0443\u0436\u0438\u0432\u0430\u043d\u0438\u0435 \u0432 \u043d\u043e\u043c\u0435\u0440\u0430\u0445, \u0444\u043e\u0442\u043e\u0433\u0440\u0430\u0444, \u043f\u0430\u0440\u0438\u043a\u043c\u0430\u0445\u0435\u0440\u0441\u043a\u0430\u044f, \u043d\u044f\u043d\u044f \u0434\u043b\u044f \u0440\u0435\u0431\u0435\u043d\u043a\u0430, \u0441\u0430\u043b\u043e\u043d \u043a\u0440\u0430\u0441\u043e\u0442\u044b, \u043f\u0440\u043e\u043a\u0430\u0442 \u0430\u0432\u0442\u043e\u043c\u043e\u0431\u0438\u043b\u0435\u0439, \u043f\u0440\u0430\u0447\u0435\u0447\u043d\u0430\u044f; \u0443\u0434\u043e\u0431\u0441\u0442\u0432\u0430 \u0434\u043b\u044f \u0438\u043d\u0432\u0430\u043b\u0438\u0434\u043e\u0432 (\u043d\u043e\u043c\u0435\u0440\u0430); \u043f\u0440\u0438\u043d\u0438\u043c\u0430\u044e\u0442\u0441\u044f \u043a\u0440\u0435\u0434\u0438\u0442\u043d\u044b\u0435 \u043a\u0430\u0440\u0442\u043e\u0447\u043a\u0438: Visa, MasterCard.<\/p><p><strong data-block-type=\"nomer\">\u041d\u041e\u041c\u0415\u0420:<\/strong><strong>superior: <\/strong>2-\u043c\u0435\u0441\u0442. (\u043c\u043e\u0436\u043d\u043e \u0440\u0430\u0437\u043c\u0435\u0441\u0442\u0438\u0442\u044c \u0434\u043e\u043f\u043e\u043b\u043d\u0438\u0442\u0435\u043b\u044c\u043d\u043e 1 \u043a\u0440\u043e\u0432\u0430\u0442\u044c), \u043e\u043a. 45 \u043c\u00b2, \u044d\u043b\u0435\u0433\u0430\u043d\u0442\u043d\u044b\u0439, \u0438\u043d\u0434\u0438\u0432\u0438\u0434\u0443\u0430\u043b\u044c\u043d\u043e \u0443\u043f\u0440\u0430\u0432\u043b\u044f\u0435\u043c\u044b\u0439 \u043a\u043e\u043d\u0434\u0438\u0446\u0438\u043e\u043d\u0435\u0440, \u0432\u0430\u043d\u043d\u0430\u044f \u043a\u043e\u043c\u043d\u0430\u0442\u0430 (\u0434\u0443\u0448 \u0438\u043b\u0438 \u0432\u0430\u043d\u043d\u0430, \u0442\u0443\u0430\u043b\u0435\u0442; \u0444\u0435\u043d), \u0441\u043f\u0443\u0442\u043d\u0438\u043a\u043e\u0432\u043e\u0435 \u0442\u0435\u043b\u0435\u0432\u0438\u0434\u0435\u043d\u0438\u0435, \u0442\u0435\u043b\u0435\u0444\u043e\u043d, \u043d\u0430\u0431\u043e\u0440 \u0434\u043b\u044f \u043a\u043e\u0444\u0435\/\u0447\u0430\u044f, \u0441\u0435\u0439\u0444, \u043c\u0438\u043d\u0438-\u0431\u0430\u0440 (\u0431\u0435\u0441\u043f\u043b\u0430\u0442\u043d\u044b\u0435 \u0431\u0435\u0437\u0430\u043b\u043a\u043e\u0433\u043e\u043b\u044c\u043d\u044b\u0435 \u043d\u0430\u043f\u0438\u0442\u043a\u0438); \u0431\u0435\u0441\u043f\u043b\u0430\u0442\u043d\u043e \u043a\u0440\u043e\u0432\u0430\u0442\u043a\u0430 \u0434\u043b\u044f \u0440\u0435\u0431\u0435\u043d\u043a\u0430 \u0434\u043e 2 \u043b\u0435\u0442 \u043f\u043e \u043f\u0440\u0435\u0434\u0432\u0430\u0440\u0438\u0442\u0435\u043b\u044c\u043d\u043e\u043c\u0443 \u0437\u0430\u043a\u0430\u0437\u0443 \u0434\u043e \u043f\u0440\u0438\u0435\u0437\u0434\u0430; \u0431\u0430\u043b\u043a\u043e\u043d \u0438\u043b\u0438 \u0442\u0435\u0440\u0440\u0430\u0441\u0430 (\u0441\u0442\u043e\u043b\u0438\u043a \u0438 \u0441\u0442\u0443\u043b\u044c\u044f).; <strong>\u0441\u0435\u043c\u0435\u0439\u043d\u044b\u0439: <\/strong>2-\u043c\u0435\u0441\u0442. (\u043c\u043e\u0436\u043d\u043e \u0440\u0430\u0437\u043c\u0435\u0441\u0442\u0438\u0442\u044c \u0434\u043e\u043f\u043e\u043b\u043d\u0438\u0442\u0435\u043b\u044c\u043d\u043e 1 \u0438\u043b\u0438 2 \u043a\u0440\u043e\u0432\u0430\u0442\u0438), \u043e\u043a. 65 \u043c\u00b2, \u043e\u0441\u043d\u0430\u0449\u0435\u043d\u0438\u0435 \u043a\u0430\u043a \u0432 \u0441\u0442\u0430\u043d\u0434\u0430\u0440\u0442\u043d\u043e\u043c \u043d\u043e\u043c\u0435\u0440\u0435, 2 \u043f\u043e\u043c\u0435\u0449\u0435\u043d\u0438\u044f \u0440\u0430\u0437\u0434\u0435\u043b\u0435\u043d\u044b \u0434\u0432\u0435\u0440\u044c\u044e; \u0432\u0438\u0434 \u043d\u0430 \u043c\u043e\u0440\u0435, \u0430 \u0442\u0430\u043a\u0436\u0435 \u0441\u0435\u043c\u0435\u0439\u043d\u044b\u0439 \u043d\u043e\u043c\u0435\u0440 \u043f\u043e \u0437\u0430\u043a\u0430\u0437\u0443, \u0437\u0430 \u0434\u043e\u043f\u043e\u043b\u043d\u0438\u0442\u0435\u043b\u044c\u043d\u0443\u044e \u043f\u043b\u0430\u0442\u0443.<\/p><p><strong data-block-type=\"sport-i-razvlecheniya\">\u0421\u041f\u041e\u0420\u0422 \u0418 \u0420\u0410\u0417\u0412\u041b\u0415\u0427\u0415\u041d\u0418\u042f: <\/strong> 2 \u0431\u0430\u0441\u0441\u0435\u0439\u043d\u0430, \u0432 \u0442\u043e\u043c \u0447\u0438\u0441\u043b\u0435 \u043e\u0434\u0438\u043d \u0441 \u043f\u043e\u0434\u043e\u0433\u0440\u0435\u0432\u043e\u043c \u0432 \u0437\u0438\u043c\u043d\u0438\u0439 \u0441\u0435\u0437\u043e\u043d, \u043d\u0435\u0440\u0435\u0433\u0443\u043b\u044f\u0440\u043d\u043e\u0439 \u0444\u043e\u0440\u043c\u044b, \u043f\u0440\u0435\u0441\u043d\u0430\u044f \u0432\u043e\u0434\u0430: \u043e\u043a. 500 \u043c\u00b2, \u0433\u043b. 1,4-1,6 \u043c, \u0431\u0430\u0441\u0441\u0435\u0439\u043d \u0434\u043b\u044f \u0434\u0435\u0442\u0435\u0439 \u0441 \u043f\u043e\u0434\u043e\u0433\u0440\u0435\u0432\u043e\u043c \u0432 \u0437\u0438\u043c\u043d\u0438\u0439 \u0441\u0435\u0437\u043e\u043d, \u043f\u0440\u0435\u0441\u043d\u0430\u044f \u0432\u043e\u0434\u0430, \u0443 \u0431\u0430\u0441\u0441\u0435\u0439\u043d\u0430 \u0431\u0435\u0441\u043f\u043b\u0430\u0442\u043d\u044b\u0435 \u0437\u043e\u043d\u0442\u044b, \u0448\u0435\u0437\u043b\u043e\u043d\u0433\u0438, \u043c\u0430\u0442\u0440\u0430\u0446\u044b \u0438 \u043f\u043e\u043b\u043e\u0442\u0435\u043d\u0446\u0430; \u0442\u0440\u0435\u043d\u0430\u0436\u0435\u0440\u043d\u044b\u0439 \u0437\u0430\u043b, \u0430\u044d\u0440\u043e\u0431\u0438\u043a\u0430, \u043f\u043b\u044f\u0436\u043d\u044b\u0439 \u0432\u043e\u043b\u0435\u0439\u0431\u043e\u043b, \u0441\u0442\u0440\u0435\u0442\u0447\u0438\u043d\u0433, \u0438\u0433\u0440\u043e\u0432\u0430\u044f \u043f\u043b\u043e\u0449\u0430\u0434\u043a\u0430 \u0438 \u043a\u043e\u043c\u043d\u0430\u0442\u0430 \u0434\u043b\u044f \u0434\u0435\u0442\u0435\u0439, \u043c\u0438\u043d\u0438-\u043a\u043b\u0443\u0431 (4-12 \u043b\u0435\u0442), \u0434\u0438\u0441\u043a\u043e\u0442\u0435\u043a\u0430, \u0430\u043d\u0438\u043c\u0430\u0446\u0438\u0438 \u0434\u043b\u044f \u0432\u0437\u0440\u043e\u0441\u043b\u044b\u0445 \u0438 \u0434\u0435\u0442\u0435\u0439; \u0437\u0430 \u043e\u0442\u0434\u0435\u043b\u044c\u043d\u0443\u044e \u043f\u043b\u0430\u0442\u0443: 4 \u0442\u0435\u043d\u043d\u0438\u0441\u043d\u044b\u0445 \u043a\u043e\u0440\u0442\u0430 \u0441 \u043e\u0441\u0432\u0435\u0449\u0435\u043d\u0438\u0435\u043c, \u0431\u0438\u043b\u044c\u044f\u0440\u0434, \u0432\u0435\u0440\u0445\u043e\u0432\u0430\u044f \u0435\u0437\u0434\u0430, \u0439\u043e\u0433\u0430, \u043c\u0438\u043d\u0438-\u0433\u043e\u043b\u044c\u0444, \u0432\u043e\u0434\u043d\u044b\u0435 \u0432\u0438\u0434\u044b \u0441\u043f\u043e\u0440\u0442\u0430 \u043d\u0430 \u043f\u043b\u044f\u0436\u0435, \u043e\u0431\u0443\u0447\u0435\u043d\u0438\u0435 \u0434\u0430\u0439\u0432\u0438\u043d\u0433\u0443; \u0441\u043f\u0430-\u0446\u0435\u043d\u0442\u0440: \u0431\u0435\u0441\u043f\u043b\u0430\u0442\u043d\u043e: \u043a\u0440\u044b\u0442\u044b\u0439 \u0431\u0430\u0441\u0441\u0435\u0439\u043d, \u0441\u0430\u0443\u043d\u0430, \u043f\u0430\u0440\u043e\u0432\u0430\u044f \u0431\u0430\u043d\u044f, \u0434\u0436\u0430\u043a\u0443\u0437\u0438; \u0437\u0430 \u043e\u0442\u0434\u0435\u043b\u044c\u043d\u0443\u044e \u043f\u043b\u0430\u0442\u0443: \u043f\u0440\u043e\u0446\u0435\u0434\u0443\u0440\u044b \u043f\u043e \u0443\u0445\u043e\u0434\u0443, \u043c\u0430\u0441\u0441\u0430\u0436.<\/p><p><strong data-block-type=\"all-inclusive\">ALL INCLUSIVE:<\/strong> \u0437\u0430\u0432\u0442\u0440\u0430\u043a (6.30-10.30), \u043f\u043e\u0437\u0434\u043d\u0438\u0439 \u0437\u0430\u0432\u0442\u0440\u0430\u043a (10.30-11.30), o\u0431\u0435\u0434 (12.00-15.00), \u0443\u0436\u0438\u043d (18.00-22.30) \u0448\u0432\u0435\u0434\u0441\u043a\u0438\u0439 \u0441\u0442\u043e\u043b \u0432 \u0433\u043b\u0430\u0432\u043d\u043e\u043c \u0440\u0435\u0441\u0442\u043e\u0440\u0430\u043d\u0435; \u0437\u0430\u043a\u0443\u0441\u043a\u0438 \u0432 \u043e\u043f\u0440\u0435\u0434\u0435\u043b\u0435\u043d\u043d\u044b\u0445 \u0431\u0430\u0440\u0430\u0445 (10.00-17.00); \u043e\u0434\u0438\u043d \u0440\u0430\u0437 \u0432\u043e \u0432\u0440\u0435\u043c\u044f \u0442\u0443\u0440\u0430 \u0443\u0436\u0438\u043d \u0432 \u0440\u0435\u0441\u0442\u043e\u0440\u0430\u043d\u0435 \u00e0 la carte (\u0442\u0440\u0435\u0431\u0443\u0435\u0442\u0441\u044f \u043f\u0440\u0435\u0434\u0432\u0430\u0440\u0438\u0442\u0435\u043b\u044c\u043d\u043e\u0435 \u0431\u0440\u043e\u043d\u0438\u0440\u043e\u0432\u0430\u043d\u0438\u0435); \u043a\u043e\u0444\u0435, \u0447\u0430\u0439 \u0438 \u043f\u0435\u0447\u0435\u043d\u044c\u0435 \u0432 \u0431\u0430\u0440\u0435 Atrium (15.00-18.00); \u0431\u0435\u0437\u0430\u043b\u043a\u043e\u0433\u043e\u043b\u044c\u043d\u044b\u0435 \u0438 \u043c\u0435\u0441\u0442\u043d\u044b\u0435 \u0430\u043b\u043a\u043e\u0433\u043e\u043b\u044c\u043d\u044b\u0435 \u043d\u0430\u043f\u0438\u0442\u043a\u0438 \u0432 \u043e\u043f\u0440\u0435\u0434\u0435\u043b\u0435\u043d\u043d\u044b\u0445 \u0431\u0430\u0440\u0430\u0445 (10.00-24.00).<\/p><p><strong data-block-type=\"kontakt\">\u041a\u041e\u041d\u0422\u0410\u041a\u0422: <\/strong> 0020\/653260700, www.palmroyaleresort.com<\/p><div data-block-type=\"besplatno\"><strong>\u0411\u0415\u0421\u041f\u041b\u0410\u0422\u041d\u041e:<\/strong><ul><li>\u043f\u043b\u044f\u0436\u043d\u044b\u0439 \u0441\u0435\u0440\u0432\u0438\u0441 <\/li><li>Wi-Fi<\/li><\/ul><\/div><p class=\"description-empty-paragraph\">\u00a0<\/p><p><em>\u0423\u043a\u0430\u0437\u0430\u043d\u043d\u043e\u0435 \u0432 \u043f\u0440\u0435\u0434\u043b\u043e\u0436\u0435\u043d\u0438\u0438 \u0432\u0440\u0435\u043c\u044f \u043f\u0438\u0442\u0430\u043d\u0438\u044f \u0430 \u0442\u0430\u043a\u0436\u0435 \u0440\u0430\u0431\u043e\u0442\u044b \u043e\u0442\u0434\u0435\u043b\u044c\u043d\u044b\u0445 \u044d\u043b\u0435\u043c\u0435\u043d\u0442\u043e\u0432 \u0438\u043d\u0444\u0440\u0430\u0441\u0442\u0440\u0443\u043a\u0442\u0443\u0440\u044b \u043e\u0442\u0435\u043b\u044f \u043c\u043e\u0436\u0435\u0442 \u0431\u044b\u0442\u044c \u0438\u0437\u043c\u0435\u043d\u0435\u043d\u043e \u0432 \u0437\u0430\u0432\u0438\u0441\u0438\u043c\u043e\u0441\u0442\u0438 \u043e\u0442 \u0441\u0435\u0437\u043e\u043d\u0430, \u043f\u043e\u0433\u043e\u0434\u043d\u044b\u0445 \u0443\u0441\u043b\u043e\u0432\u0438\u0439, \u043d\u0430 \u043f\u0440\u043e\u0441\u044c\u0431\u0443 \u0433\u043e\u0441\u0442\u0435\u0439 \u0438\u043b\u0438 \u043f\u043e \u0444\u043e\u0440\u0441-\u043c\u0430\u0436\u043e\u0440\u043d\u044b\u043c \u043e\u0431\u0441\u0442\u043e\u044f\u0442\u0435\u043b\u044c\u0441\u0442\u0432\u0430\u043c.<\/em><\/p><p class=\"description-empty-paragraph\">\u00a0<\/p> <\/div>[gmaps lat=\"26.837137 \" lng=\"33.948816\"]"}